Metadata-Version: 2.1
Name: NCBI-Companion
Version: 2.1.1
Summary: NCBI_Companion assists you to build a reference database with a fasta and a mapping file through Genbank
Home-page: https://github.com/lixiaopi1985/NCBI_Companion
Author: Xiaoping Li
Author-email: lixiaopi@oregonstate.edu
License: UNKNOWN
Platform: UNKNOWN
Classifier: Development Status :: 3 - Alpha
Classifier: Programming Language :: Python :: 3
Classifier: License :: OSI Approved :: MIT License
Classifier: Operating System :: POSIX :: Linux
